GUI.py
IK.py
ML.py
Params.py
dataset.py
main.py
realtest.py
test.py
pythongui_roxy-0.1.0.dist-info/METADATA
pythongui_roxy-0.1.0.dist-info/WHEEL
pythongui_roxy-0.1.0.dist-info/entry_points.txt
pythongui_roxy-0.1.0.dist-info/top_level.txt
pythongui_roxy-0.1.0.dist-info/RECORD
