Metadata-Version: 2.1
Name: pythongui_roxy
Version: 0.1.0
Requires-Dist: pandas
Requires-Dist: numpy
Requires-Dist: scikit-learn
Requires-Dist: scipy
Requires-Dist: torch
Requires-Dist: PyQt5
